MANIFEST.in
README.md
setup.py
carp_compression/CARP.py
carp_compression/SMC.py
carp_compression/__init__.py
carp_compression.egg-info/PKG-INFO
carp_compression.egg-info/SOURCES.txt
carp_compression.egg-info/dependency_links.txt
carp_compression.egg-info/requires.txt
carp_compression.egg-info/top_level.txt
src/helper.cpp
src/helper.hpp
src/py_tree.cpp
src/tree_class.cpp
src/tree_class.hpp