Metadata-Version: 2.1
Name: carp-compression
Version: 0.1.3
Summary: use CARP to compress image
Home-page: https://github.com/xylimeng/BayesCompression
Author: Yifan Tao
Author-email: 2019302020078@whu.edu.cn
License: MIT
Classifier: License :: OSI Approved :: MIT License
Classifier: Programming Language :: Python
Classifier: Programming Language :: Python :: 3
Classifier: Programming Language :: Python :: Implementation :: CPython
Requires-Python: >=3.9
